_solib_k8/__init__.py
_solib_k8/libexternal_Sclif_Slibcpp_Uruntime.so
_solib_k8/libexternal_Scom_Ugoogle_Uabsl_Sabsl_Sbase_Slibbase.so
_solib_k8/libexternal_Scom_Ugoogle_Uabsl_Sabsl_Sbase_Slibdynamic_Uannotations.so
_solib_k8/libexternal_Scom_Ugoogle_Uabsl_Sabsl_Sbase_Slibmalloc_Uinternal.so
_solib_k8/libexternal_Scom_Ugoogle_Uabsl_Sabsl_Sbase_Slibspinlock_Uwait.so
_solib_k8/libexternal_Scom_Ugoogle_Uabsl_Sabsl_Sbase_Slibthrow_Udelegate.so
_solib_k8/libexternal_Scom_Ugoogle_Uabsl_Sabsl_Sdebugging_Slibdebugging_Uinternal.so
_solib_k8/libexternal_Scom_Ugoogle_Uabsl_Sabsl_Sdebugging_Slibdemangle_Uinternal.so
_solib_k8/libexternal_Scom_Ugoogle_Uabsl_Sabsl_Sdebugging_Slibstacktrace.so
_solib_k8/libexternal_Scom_Ugoogle_Uabsl_Sabsl_Sdebugging_Slibsymbolize.so
_solib_k8/libexternal_Scom_Ugoogle_Uabsl_Sabsl_Snumeric_Slibint128.so
_solib_k8/libexternal_Scom_Ugoogle_Uabsl_Sabsl_Sstrings_Slibinternal.so
_solib_k8/libexternal_Scom_Ugoogle_Uabsl_Sabsl_Sstrings_Slibstrings.so
_solib_k8/libexternal_Scom_Ugoogle_Uabsl_Sabsl_Ssynchronization_Slibgraphcycles_Uinternal.so
_solib_k8/libexternal_Scom_Ugoogle_Uabsl_Sabsl_Ssynchronization_Slibsynchronization.so
_solib_k8/libexternal_Scom_Ugoogle_Uabsl_Sabsl_Stime_Sinternal_Scctz_Slibcivil_Utime.so
_solib_k8/libexternal_Scom_Ugoogle_Uabsl_Sabsl_Stime_Sinternal_Scctz_Slibtime_Uzone.so
_solib_k8/libexternal_Scom_Ugoogle_Uabsl_Sabsl_Stime_Slibtime.so
_solib_k8/libexternal_Scom_Ugoogle_Uabsl_Sabsl_Stypes_Slibbad_Uoptional_Uaccess.so
_solib_k8/libexternal_Scom_Ugoogle_Uabsl_Sabsl_Stypes_Sliboptional.so
_solib_k8/libexternal_Scom_Ugooglesource_Ucode_Ure2_Slibre2.so
_solib_k8/libexternal_Sdouble_Uconversion_Slibdouble-conversion.so
_solib_k8/libexternal_Sfarmhash_Uarchive_Slibfarmhash.so
_solib_k8/libexternal_Sfft2d_Slibfft2d.so
_solib_k8/libexternal_Sgif_Uarchive_Slibgif.so
_solib_k8/libexternal_Shighwayhash_Slibarch_Uspecific.so
_solib_k8/libexternal_Shighwayhash_Slibsip_Uhash.so
_solib_k8/libexternal_Shtslib_Slibhtslib.so
google_nucleus-0.2.2.dist-info/LICENSE
google_nucleus-0.2.2.dist-info/METADATA
google_nucleus-0.2.2.dist-info/WHEEL
google_nucleus-0.2.2.dist-info/top_level.txt
google_nucleus-0.2.2.dist-info/RECORD
