Metadata-Version: 2.1
Name: google-nucleus
Version: 0.2.2
Summary: A library for reading and writing genomics data.
Home-page: https://github.com/google/nucleus
Author: The Genomics team in Google Brain
Author-email: nucleus-public@google.com
License: Apache 2.0
Project-URL: Source, https://github.com/google/nucleus
Project-URL: Bug Reports, https://github.com/google/nucleus/issues
Keywords: genomics tensorflow bioinformatics
Platform: UNKNOWN
Classifier: Development Status :: 4 - Beta
Classifier: Intended Audience :: Developers
Classifier: Intended Audience :: Healthcare Industry
Classifier: Intended Audience :: Science/Research
Classifier: License :: OSI Approved :: Apache Software License
Classifier: Operating System :: POSIX :: Linux
Classifier: Programming Language :: Python
Classifier: Topic :: Scientific/Engineering :: Bio-Informatics
Classifier: Topic :: Software Development :: Libraries :: Python Modules
Requires-Dist: contextlib2
Requires-Dist: intervaltree
Requires-Dist: absl-py
Requires-Dist: mock
Requires-Dist: numpy
Requires-Dist: six
Requires-Dist: tensorflow (>=1.11.0)
